README.md
setup.py
pyautocast/__init__.py
pyautocast/_autocast.py
pyautocast.egg-info/PKG-INFO
pyautocast.egg-info/SOURCES.txt
pyautocast.egg-info/dependency_links.txt
pyautocast.egg-info/requires.txt
pyautocast.egg-info/top_level.txt