Metadata-Version: 2.1
Name: pyautocast
Version: 0.1.1
Summary: Automatic function arguments casting
Home-page: https://github.com/ctgk/pyautocast
Author: ctgk
Author-email: r1135nj54w@gmail.com
Maintainer: ctgk
Maintainer-email: r1135nj54w@gmail.com
License: MIT
Platform: UNKNOWN
Classifier: Programming Language :: Python :: 3.7
Classifier: Programming Language :: Python :: 3.8
Classifier: License :: OSI Approved :: MIT License
Requires-Python: >=3.7
Provides-Extra: develop
